DBSkr/__init__.py
DBSkr/assets.py
DBSkr/client.py
DBSkr/enums.py
DBSkr/errors.py
DBSkr/https.py
DBSkr/models.py
DBSkr/koreanbots/__init__.py
DBSkr/koreanbots/api.py
DBSkr/koreanbots/client.py
DBSkr/koreanbots/enums.py
DBSkr/koreanbots/errors.py
DBSkr/koreanbots/flags.py
DBSkr/koreanbots/https.py
DBSkr/koreanbots/models.py
DBSkr/koreanbots/widget.py
DBSkr/topgg/__init__.py
DBSkr/topgg/api.py
DBSkr/topgg/client.py
DBSkr/topgg/enums.py
DBSkr/topgg/errors.py
DBSkr/topgg/https.py
DBSkr/topgg/models.py
DBSkr/topgg/widget.py
DBSkr/uniquebots/__init__.py
DBSkr/uniquebots/api.py
DBSkr/uniquebots/client.py
DBSkr/uniquebots/enums.py
DBSkr/uniquebots/errors.py
DBSkr/uniquebots/https.py
DBSkr/uniquebots/models.py
DBSKR-2.0.dist-info/LICENSE
DBSKR-2.0.dist-info/METADATA
DBSKR-2.0.dist-info/WHEEL
DBSKR-2.0.dist-info/top_level.txt
DBSKR-2.0.dist-info/RECORD
