Metadata-Version: 2.1
Name: DBSKR
Version: 2.0
Summary: A python wrapper for KoreanBots, top.gg and UniqueBots
Home-page: https://github.com/gunyu1019/DBSkr-py
Author: gunyu1019
Author-email: gunyu1019@gmail.com
License: MIT
Project-URL: Coverage: codacy, https://app.codacy.com/gh/gunyu1019/DBSkr-py/dashboard
Project-URL: Coverage: codefactor, https://www.codefactor.io/repository/github/gunyu1019/dbskr-py
Project-URL: GitHub: issues, https://github.com/gunyu1019/DBSkr-py/issues
Project-URL: GitHub: repo, https://github.com/gunyu1019/DBSkr-py
Platform: UNKNOWN
Classifier: Development Status :: 5 - Production/Stable
Classifier: License :: OSI Approved :: MIT License
Classifier: Intended Audience :: Developers
Classifier: Natural Language :: Korean
Classifier: Programming Language :: Python
Classifier: Programming Language :: Python :: 3
Classifier: Programming Language :: Python :: 3.7
Classifier: Programming Language :: Python :: 3.8
Classifier: Programming Language :: Python :: 3.9
Classifier: Topic :: Internet
Classifier: Topic :: Software Development :: Libraries
Classifier: Topic :: Software Development :: Libraries :: Python Modules
Classifier: Topic :: Utilities
Requires-Python: >=3.7
Requires-Dist: asyncio
Requires-Dist: aiohttp
Requires-Dist: discord.py
